llm_roleplay/__init__.py
llm_roleplay/actions/__init__.py
llm_roleplay/actions/dialogue_generator.py
llm_roleplay/configs/__init__.py
llm_roleplay/configs_tamoyan/__init__.py
tests/__init__.py
tests/test_roleplay.py
llm_roleplay-2.0.7.dist-info/LICENSE
llm_roleplay-2.0.7.dist-info/METADATA
llm_roleplay-2.0.7.dist-info/NOTICE
llm_roleplay-2.0.7.dist-info/WHEEL
llm_roleplay-2.0.7.dist-info/top_level.txt
llm_roleplay-2.0.7.dist-info/RECORD
