Metadata-Version: 2.1
Name: llm-roleplay
Version: 2.0.7
Summary: LLM Roleplay: Simulating Human-Chatbot Interaction
Requires-Python: >=3.10.0
License-File: LICENSE
License-File: NOTICE
Requires-Dist: urartu
Requires-Dist: jsonlines
Requires-Dist: tiktoken
Requires-Dist: langchain
Requires-Dist: langchain-openai
